pabui/__init__.py
pabui/commands.py
pabui/config.py
pabui/extensions.py
pabui/views.py
pabui/api/__init__.py
pabui/api/app.py
pabui/api/config.py
pabui/api/contracts.py
pabui/api/strategies.py
pabui/api/tasks.py
pabui/api/utils.py
pabui/lib/__init__.py
pabui/lib/app.py
pabui/lib/contracts.py
pabui/lib/strategies.py
pabui/lib/utils.py
pabui/static/bundle.css
pabui/static/bundle.js
pabui/static/bundle.js.map
pabui/static/global.css
pabui/templates/index.html
pabui-0.1.dist-info/METADATA
pabui-0.1.dist-info/WHEEL
pabui-0.1.dist-info/entry_points.txt
pabui-0.1.dist-info/top_level.txt
pabui-0.1.dist-info/RECORD
