Metadata-Version: 2.1
Name: pabui
Version: 0.1
Summary: PABUI is a GUI for PAB projects.
Home-page: https://github.com/manuelpepe/PABUI
Author: Manuel Pepe
Author-email: manuelpepe-dev@outlook.com.ar
License: UNKNOWN
Platform: UNKNOWN
Requires-Dist: flask
Requires-Dist: PyAutoBlockchain
